setup.cfg
setup.py
bender/__init__.py
bender/bender.py
bender/decorators.py
bender/exceptions.py
bender.egg-info/PKG-INFO
bender.egg-info/SOURCES.txt
bender.egg-info/dependency_links.txt
bender.egg-info/requires.txt
bender.egg-info/top_level.txt