Metadata-Version: 1.1
Name: bender
Version: 0.0.4
Summary: Telegram bot framework
Home-page: https://git.hso.rocks/hso/bender
Author: José Sazo
Author-email: jose.sazo@gmail.com
License: UNKNOWN
Download-URL: https://git.hso.rocks/hso/bender/archive/0.0.4.tar.gz
Keywords: text,api,bot
Platform: UNKNOWN
Classifier: Development Status :: 3 - Alpha
Classifier: Programming Language :: Python :: 2
Classifier: Programming Language :: Python :: 2.7
Classifier: Programming Language :: Python :: 3
Classifier: Programming Language :: Python :: 3.4
